eject_applet/__init__.py
eject_applet/main.py
eject_applet/data/help.txt
eject_applet-0.1.1.dist-info/LICENSE
eject_applet-0.1.1.dist-info/METADATA
eject_applet-0.1.1.dist-info/WHEEL
eject_applet-0.1.1.dist-info/entry_points.txt
eject_applet-0.1.1.dist-info/top_level.txt
eject_applet-0.1.1.dist-info/RECORD
