Metadata-Version: 2.1
Name: eject-applet
Version: 0.1.1
Summary: Simple external disk manager for Linux
Home-page: https://github.com/Akmadan23/eject-applet
Author: Azad Ahmadi
Author-email: azadahmadi@mailo.com
License: GPL-3
Classifier: Programming Language :: Python :: 3
Classifier: License :: OSI Approved :: GNU General Public License (GPL)
Classifier: Operating System :: POSIX :: Linux
Requires-Python: >=3.6
License-File: LICENSE
Requires-Dist: PyGObject
